mach/__init__.py
mach/_array_api.py
mach/_check.py
mach/_cuda_impl.cpython-310-x86_64-linux-gnu.so
mach/_cuda_impl.pyi
mach/_vis.py
mach/experimental.py
mach/geometry.py
mach/kernel.cu
mach/kernel.py
mach/wavefront.py
mach/io/__init__.py
mach/io/must.py
mach/io/uff.py
mach/io/utils.py
mach/vendor/helper_cuda.h
mach/vendor/helper_math.h
mach_beamform-0.1.1.dist-info/METADATA
mach_beamform-0.1.1.dist-info/WHEEL
mach_beamform-0.1.1.dist-info/RECORD
mach_beamform-0.1.1.dist-info/licenses/LICENSE.md
