Metadata-Version: 2.1
Name: mach-beamform
Version: 0.1.1
Summary: Ultrafast GPU-accelerated beamforming kernel for ultrasound imaging
Keywords: beamforming,delay and sum,ultrasound,python,cuda
Author: Charles Guan, Gianmarco Pinton, Alex Rockhill
Maintainer: Charles Guan, Gustavo Zago Canal
Classifier: Intended Audience :: Developers
Classifier: Programming Language :: Python
Classifier: Programming Language :: Python :: 3
Classifier: Programming Language :: Python :: 3.10
Classifier: Programming Language :: Python :: 3.11
Classifier: Programming Language :: Python :: 3.12
Classifier: Programming Language :: Python :: 3.13
Classifier: Topic :: Software Development :: Libraries :: Python Modules
Project-URL: Repository, https://github.com/Forest-Neurotech/mach
Requires-Python: <3.14,>=3.10
Requires-Dist: array-api-compat>=1.11.0
Requires-Dist: einops>=0.8.0
Requires-Dist: jaxtyping>=0.2.36
Provides-Extra: uff
Requires-Dist: pyuff_ustb>=0.1.0; extra == "uff"
Requires-Dist: scipy>=1.13.1; extra == "uff"
Requires-Dist: numpy>=1.25.0; extra == "uff"
Provides-Extra: vis
Requires-Dist: matplotlib>=3.9.4; extra == "vis"
Requires-Dist: colorcet>=3.1.0; extra == "vis"
Provides-Extra: examples
Requires-Dist: pymust>=0.1.8; extra == "examples"
Requires-Dist: requests>=2.25.0; extra == "examples"
Requires-Dist: mach-beamform[vis]; extra == "examples"
Provides-Extra: all
Requires-Dist: tqdm>=4.65.0; extra == "all"
Requires-Dist: cupy-cuda12x>=12.0.0; extra == "all"
Requires-Dist: mach-beamform[examples,uff,vis]; extra == "all"
